pyvesynclevoit
