Metadata-Version: 2.1
Name: pyvesynclevoit
Version: 1.4.3
Summary: pyvesynclevoit is a library to manage Etekcity                 Devices and Levoit Air Purifier                 clone and thanks to webdjoe
Home-page: https://github.com/andreasekoyoga/pyvesynclevoit
Author: Andreas
Author-email: andreasekoyoga@gmail.com
License: MIT
Keywords: iot,vesync,levoit,etekcity
Platform: UNKNOWN
Classifier: License :: OSI Approved :: MIT License
Classifier: Intended Audience :: Developers
Classifier: Intended Audience :: End Users/Desktop
Classifier: Natural Language :: English
Classifier: Programming Language :: Python :: 3.6
Requires-Python: >=3.6
